rlmarlbot_plugin/__init__.py
rlmarlbot_plugin/base_plugin.py
rlmarlbot_plugin-0.1.7.dist-info/METADATA
rlmarlbot_plugin-0.1.7.dist-info/WHEEL
rlmarlbot_plugin-0.1.7.dist-info/RECORD
